[
    { "url": "http://www.skysbuchrezensionen.de" },
    { "url": "https://schluesselreiz.blogspot.de" },
    { "url": "https://kristin84.blogspot.de" },
    {
        "url": "http://buecherparadies.eu",
        "articleSelector": ".item"
    },
    { "url": "https://sue-timeless.blogspot.de" },
    {
        "url": "http://kaffeehaussitzer.de",
        "feed_ignore": true
    },
    {
        "url": "http://lese-liebe.com",
        "frame": "https://lebensleseliebelust.blogspot.de/",
        "feed": "https://lebensleseliebelust.blogspot.de/feeds/posts/default"
    },
    {
        "url": "https://carobloggt.blogspot.de",
        "articleSelector": ".post"
    },
    { "url": "https://fantastikbooks.blogspot.de" },
    { "url": "https://www.lesestunden.de" },
    { "url": "https://beatelovelybooks.blogspot.de" },
    { "url": "https://atalantes.de" },
    { "url": "https://ichlesehaltgern.com" },
    { "url": "https://ninasbuecher.blogspot.de" },
    { "url": "http://www.buechernische-blog.de" },
    { "url": "https://abookshelffullofsunshine.blogspot.de" },
    { "url": "https://diewunderbareweltderjane.wordpress.com" },
    {
        "url": "http://blog.literaturwelt.de",
        "isArticlePagePattern": "/archiv/*",
        "titleSelector": ".weblogItem h3",
        "dateSelector": ".wiMeta",
        "articleSelector": ".wiText"
    },
    { "url": "http://www.cupcatz.de" },
    { "url": "http://sarahsuperwoman.de", "feed": "http://sarahsuperwoman.de/feed" },
    { "url": "https://sofiasworldofbooks.blogspot.de" },
    { "url": "https://bookrecession.wordpress.com" },
    { "url": "https://kathrinsbooklove.wordpress.com" },
    { "url": "https://annrosestyle.blogspot.de" },
    { "url": "http://www.anis-allerlei.de" },
    { "url": "https://vergessenebuecher.blogspot.de" },
    { "url": "http://www.sonnysblog.de" },
    { "url": "http://www.buecherkaffee.de" },
    { "url": "http://www.lenasweltderbuecher.de" },
    { "url": "https://fragmentage.blogspot.de" },
    { "url": "https://buechertraume.blogspot.de" },
    { "url": "https://worldofbooks4.blogspot.de" },
    {
        "url": "http://www.lazyliterature.de",
        "dateSelector": ".updated"
    },
    { "url": "https://www.lovelymix.de" },
    {
        "url": "https://www.buecherkinder.de/blog",
        "feed": "https://www.buecherkinder.de/rss/",
        "simulateBrowser": true
    },
    { "url": "http://pudelmuetzes-welt.de" },
    { "url": "https://wortakzente.wordpress.com" },
    { "url": "https://projekt-ghostreader.blogspot.de" },
    { "url": "https://jujusbuecherkiste.blogspot.de" },
    { "url": "http://www.bibliofeles.de" },
    {
        "url": "http://nightingale-blog.net",
        "useFallbackDateFromUrl": true,
        "articleSelector": ".post_content"
    },
    { "url": "https://monesleseinsel.blogspot.de" },
    { "url": "https://scriptdoktor.blogspot.de" },
    { "url": "https://ninahasse.wordpress.com" },
    { "url": "http://mem-o-ries.de" },
    { "url": "http://www.papiergefluester.com" },
    { "url": "https://rawrpunx.blogspot.de" },
    {
        "url": "https://www.legimus.de",
        "titleSelector": "article h1"

    },
    { "url": "https://buchpost.wordpress.com" },
    { "url": "https://theshadowofdragonfly.blogspot.de" },
    { "url": "http://claudis-gedankenwelt.de" },
    { "url": "https://scattysbuecherblog.blogspot.de" },
    { "url": "https://chiasbuecherecke.blogspot.de" },
    { "url": "https://nallasbuecherkiste.blogspot.de" },
    { "url": "http://letteraturen.letterata.de", "feed": "http://letteraturen.letterata.de/feed/" },
    { "url": "https://buchgefieder.blogspot.de" },
    { "url": "http://www.cinemainmyhead.de" },
    { "url": "https://www.diebuchbloggerin.de" },
    { "url": "http://www.katzemitbuch.de" },
    { "url": "http://www.querbeet-gelesen.de" },
    { "url": "http://www.lilstar.de" },
    { "url": "http://www.reziratte.de" },
    { "url": "https://bookseduction.blogspot.de" },
    { "url": "http://www.hannaslovelybooks.de" },
    { "url": "https://dasbuechereulenparadies.blogspot.de" },
    {
        "url": "http://www.buchjunkies-blog.de",
        "isArticlePagePattern": "(reviewId)",
        "dateSelector": ".rezitableleft",
        "titleSelector": "h2",
        "articleSelector": ".mytext",
        "removeRegex": ["</h1>.*<p style=\"margin-top: \\-10px; text-shadow: #000 1px 1px 2px;\">"]
    },
    { "url": "https://ricas-fantastische-buecherwelt.blogspot.de" },
    { "url": "https://girlbehindbooks.blogspot.de" },
    { "url": "https://nenatie.blogspot.de" },
    { "url": "https://bloggingrenate.blogspot.de" },
    { "url": "https://pimisbuecher.wordpress.com" },
    { "url": "http://www.ninespo.de" },
    { "url": "http://www.nordbreze.de" },
    { "url": "https://littlebooktown.blogspot.de" },
    { "url": "https://krimimimi.com" },
    {
        "url": "http://zweilesen.de",
        "isArticlePageSelector": ".entry-date"
    },
    { "url": "https://tinesbuecherwelt.wordpress.com" },
    { "url": "http://nellysleseecke.de" },
    { "url": "https://sunnysbuecherschloss.blogspot.de" },
    { "url": "https://fusseligebuecherwuermer.de", "feed": "http://feeds.feedburner.com/FusseligeBuecherwuermer" },
    { "url": "http://www.leselurch.de" },
    { "url": "https://casusangelus.blogspot.de" },
    { "url": "https://blog4aleshanee.blogspot.de" },
    { "url": "http://www.phantasienreisen.de" },
    {
        "url": "https://wassollichlesen.blogspot.de",
        "titleSelector": ".entry-content h2"
    },
    { "url": "https://zwiebelchens-plauderecke.blogspot.de" },
    { "url": "http://www.librimania.de/blog/" },
    { "url": "https://privatkino.org" },
    {
        "url": "http://www.buch-rezension.eu",
        "dateSelector": ".meta"
    },
    { "url": "https://lesezauber.net" },
    { "url": "http://www.die-leselust.de" },
    { "url": "https://literaturundfeuilleton.wordpress.com" },
    { "url": "https://manjasbuchregal.de" },
    { "url": "http://lilienlicht.de" },
    { "url": "https://julesbunteweltderbuecher.blogspot.de" },
    { "url": "http://literatwo.de" },
    { "url": "https://lesenliebentraeumen.blogspot.de" },
    { "url": "https://buchkuschlerin.blogspot.de" },
    { "url": "https://birtheslesezeit.wordpress.com" },
    { "url": "https://buchstabenfaengerin.wordpress.com" },
    { "url": "https://wirlesencommunity.wordpress.com" },
    { "url": "http://www.mikkaliest.de" },
    { "url": "https://wordpress.mikkaliest.de" },
    { "url": "https://radiergummi.wordpress.com" },
    { "url": "http://buecher-monster.de" },
    { "url": "http://kielfeder-blog.de" },
    { "url": "https://meinelieblingsbooks.blogspot.de" },
    { "url": "http://www.katesleselounge.de" },
    { "url": "https://chaosqueeninaction.wordpress.com" },
    { "url": "https://readindie.wordpress.com" },
    { "url": "http://yvonnes-buecherecke.de", "feed": "http://yvonnes-buecherecke.de/feed/" },
    { "url": "https://linejasmin.blogspot.de" },
    { "url": "http://www.hisandherbooks.de" },
    { "url": "http://www.romanticbookfan.de" },
    { "url": "https://daisyandbooks.wordpress.com" },
    {
        "url": "http://lesekreis.org",
        "titleSelector": ".post h2"
    },
    { "url": "https://buecherohneende.blogspot.de" },
    { "url": "https://sunnyslesewelt.blogspot.de" },
    { "url": "https://www.mandysbuecherecke.de" },
    {
        "url": "https://meineliteratour.blogspot.de",
        "titleSelector": ".blog-posts .post h3.post-title"
    },
    { "url": "https://katjas-lesewolke.blogspot.de" },
    { "url": "https://buchstapelweise.wordpress.com" },
    { "url": "http://www.kerstin-herbert.de" },
    {
        "url": "http://www.bonaventura.blog",
        "isArticlePagePattern": "\\d{4}/"
    },
    {
        "url": "https://frau-hemingway.de",
        "titleSelector": ".post-title h1"
    },
    { "url": "http://whoiskafka.de" },
    { "url": "https://klappentexterin.wordpress.com" },
    { "url": "https://julis-leseecke.blogspot.de" },
    { "url": "https://herzgedanke.com" },
    { "url": "https://inas-little-bakery.blogspot.de" },
    { "url": "http://lesenlebenlachen.de" },
    { "url": "https://lesenslust.wordpress.com" },
    {
        "url": "http://tasmetu.de",
        "titleSelector": ".post--header h1"
    },
    { "url": "http://www.mybookblog.de" },
    { "url": "https://binchensbuecher.blogspot.de" },
    { "url": "https://griinsekatzes-leseecke.blogspot.de" },
    { "url": "http://www.tintenmeer.de", "feed": "http://www.tintenmeer.de/feed" },
    { "url": "https://dasdebuet.com" },
    { "url": "https://buecherparadis.blogspot.de" },
    { "url": "https://lesenundmehr.wordpress.com" },
    { "url": "https://lovinbooks4ever.blogspot.de" },
    { "url": "https://missrosesbuecherwelt.blogspot.de" },
    { "url": "https://www.54books.de" },
    {
        "url": "https://www.lesefieber.ch",
        "isArticlePagePattern": "(buchbesprechungen/)"
    },
    { "url": "http://www.katis-buecherwelt.de" },
    { "url": "https://claudias-buecherregal.blogspot.de" },
    { "url": "https://muromez.com" },
    { "url": "https://wortmagieblog.wordpress.com" },
    { "url": "https://kueckibooks.blogspot.de" },
    { "url": "https://anettsbuecherwelt.blogspot.de" },
    { "url": "https://umblaettern.com" },
    { "url": "https://lectureoflife.wordpress.com" },
    { "url": "https://tintenhain.wordpress.com" },
    { "url": "http://www.dieliebezudenbuechern.de" },
    { "url": "http://life4books.de" },
    { "url": "https://www.ankas-geblubber.de", "frame": "http://ankas-geblubber.blogspot.de", "feed": "http://ankas-geblubber.blogspot.de/feeds/posts/default" },
    { "url": "http://buzzaldrins.de" },
    { "url": "https://caterinaseneva.wordpress.com" },
    {
        "url": "http://www.buchsaiten.de",
        "simulateBrowser": true
    },
    { "url": "https://leselustleseliebe.wordpress.com" },
    {
        "url": "http://sommermaedchenswelt.sc-v.de",
        "frame": "http://1.xn--sommermdchenswelt-wqb.de"
    },
    { "url": "https://buechernest.blogspot.de" },
    { "url": "https://diefabelhafteweltderbuecher.blogspot.de" },
    { "url": "http://flying-thoughts.de" },
    {
        "url": "http://christinas-buchwelt.de",
        "isArticlePagePattern": "/?p=",
        "dateSelector": ".post-top h3"
    },
    { "url": "https://www.buecherleser.com" },
    { "url": "https://stefanmesch.wordpress.com" },
    { "url": "https://lillemorsfrauenliteratur.blogspot.de" },
    { "url": "https://phileablog.wordpress.com" },
    { "url": "http://zeilenkino.de" },
    { "url": "http://www.readpack.de" },
    { "url": "http://buecherblog.org" },
    { "url": "http://www.misswatson.de" },
    { "url": "https://petra-liest.blogspot.de" },
    {
        "url": "http://ilsebillslesezeichen.de",
        "isArticlePageSelector": ".entry-footer"
    },
    { "url": "http://www.buchkolumne.de" },
    { "url": "https://fraencisdaencis.de" },
    { "url": "http://www.buecher-wie-sterne.de" },
    { "url": "https://literaturlese.wordpress.com" },
    { "url": "https://feinerbuchstoff.wordpress.com" },
    {
        "url": "http://buecher.ueber-alles.net",
        "isArticlePagePattern": "/?p=",
        "dateSelector": ".post-footer"
    },
    { "url": "https://krimikiosk.blogspot.de" },
    { "url": "https://annalenaslesestuebchen.wordpress.com" },
    { "url": "https://darkfairyssenf.com" },
    { "url": "https://primeballerinasbooks.com" },
    { "url": "https://kristineliest.blogspot.de" },
    { "url": "https://sabzbooks.blogspot.de" },
    { "url": "http://www.elementareslesen.de" },
    { "url": "http://www.eltragalibros.de" },
    { "url": "http://dunkelbunt-blog.de" },
    { "url": "https://redenistsilberlesenistgold.blogspot.de" },
    { "url": "https://buecherblogger.wordpress.com" },
    { "url": "https://thomasbrasch.wordpress.com" },
    { "url": "https://buchrevier.com" },
    { "url": "http://buchkind-blog.de" },
    { "url": "http://www.leseleidenschaft.de" },
    { "url": "https://ein-guter-tag-schwerin.com" },
    { "url": "https://buchbria.blogspot.de" },
    {
        "url": "https://readingtidbits.blogspot.de",
        "titleSelector": ".title a:nth-child(2)"
    },
    { "url": "https://the-bookthief.blogspot.de" },
    {
        "url": "http://www.leselieber.de",
        "feed": "http://www.leselieber.de/feed/",
        "isArticlePageSelector": ".single",
        "dateSelector": ".post p.author",
        "titleSelector": ".post header h2",
        "articleSelector": "div.entry"
    },
    {
        "url": "http://www.mein-lesetipp.de",
        "titleSelector": ".post h3.title"
    },
    {
        "url": "http://www.schmoekermaedchen.de",
        "useFallbackDateFromUrl": true
    },
    { "url": "https://kathrineverdeen.blogspot.de" },
    { "url": "https://buchundebook.blogspot.de" },
    { "url": "https://katja-welt-book.blogspot.de" },
    { "url": "https://suechtignachbuechern.blogspot.de" },
    { "url": "https://1001buecher.wordpress.com" },
    { "url": "https://ebook-sonar.blogspot.de" },
    { "url": "http://literatourismus.net" },
    { "url": "https://lesen.abs-textandmore.de" },
    { "url": "http://buecherjunky.de" },
    { "url": "http://gutowsky-online.de" },
    { "url": "https://herzpotenzial.com" },
    { "url": "https://literarischer.blogspot.de" },
    { "url": "https://friedhofdervergessenenbuecher.blogspot.de" },
    { "url": "https://babsleben.blogspot.de" },
    { "url": "https://scriptoflife-buecherblog.blogspot.de" },
    {
        "url": "https://saetzeundschaetze.com",
        "titleSelector": ".blog-post-single-title",
        "articleSelector": ".blog-post-single-content"
    },
    { "url": "https://dasbestebuchderwelt.de" },
    { "url": "https://neonwilderness.net" },
    { "url": "http://kasasbuchfinder.de" },
    { "url": "https://juliasbuchblog.blogspot.de" },
    { "url": "https://dasgrauesofa.com" },
    { "url": "https://secretsofrock.net" },
    { "url": "http://blog.edgeofthewild.de" },
    { "url": "https://www.broesels-buecherregal.de" },
    { "url": "https://buchwolf.wordpress.com" },
    { "url": "https://lustauflesen.de" },
    { "url": "http://www.fantastische-buecherwelt.de" },
    { "url": "http://wilkosteffens.de" },
    {
        "url": "https://www.literatur-blog.at",
        "feed": "https://www.literatur-blog.at/feed/",
        "titleSelector": ".storycontent h2",
        "dateSelector": ".meta",
        "articleSelector": ".storycontent"
    },
    {
        "url": "http://www.bluecher.blog",
        "articleSelector": "article.single"
    },
    { "url": "https://buecherliebhaberin.wordpress.com" },
    { "url": "https://leseeule2709.wordpress.com" },
    { "url": "https://astrolibrium.wordpress.com" },
    {
        "url": "http://www.buchbegegnungen.de",
        "dateSelector": ".entry-meta-top"
    },
    { "url": "https://steglitzmind.wordpress.com" },
    { "url": "https://wondersbuecherkiste.blogspot.de" },
    { "url": "https://nusscookies-buecherliebe.blogspot.de" },
    {
        "url": "http://www.hallo-buch.de",
        "isArticlePageSelector": ".content .image",
        "dateSelector": ".datum",
        "titleSelector": ".content h1",
        "articleSelector": "div.content",
        "removeSelector": [".wThema"]
    },
    { "url": "http://www.kossis-welt.de/blog" },
    { "url": "http://lesarten.com" },
    { "url": "https://natzes-leseecke.blogspot.de" },
    { "url": "https://buecherwuermchenswelt.blogspot.de" },
    {
        "url": "https://nickislesewelt.blogspot.de",
        "titleSelector": "title"
    },
    { "url": "https://crimenoir.wordpress.com" },
    { "url": "https://druckbuchstaben.blogspot.de" },
    {
        "url": "http://novelero.de",
        "simulateBrowser": true
    },
    {
        "url": "http://www.nobody-knows.eu",
        "feed": "http://feeds.feedburner.com/nobody-knows",
        "frame": "http://nobody-knows.bplaced.net/wordpress/",
        "titleSelector": ".post h2.title",
        "dateSelector": ".post div.datum",
        "articleSelector": ".post .entry"
    },
    { "url": "http://www.beautybooks.at" },
    {
        "url": "https://analoglesen.wordpress.com",
        "titleSelector": ".post h1.entry-title",
        "removeSelector": ["#jp-relatedposts"],
        "articleSelector": ".post"
    },
    { "url": "https://schatzichwilleinbuchvondir.blogspot.de" },
    { "url": "https://the-lines-between.blogspot.de" },
    { "url": "https://kinderohren.wordpress.com" },
    { "url": "https://dk-literatur.blogspot.de" },
    { "url": "https://tanjaisaddictedto.blogspot.de" },
    { "url": "https://tintenzauber.wordpress.com" },
    { "url": "https://bookwives.de" },
    { "url": "http://www.liesdochmaldas.de" },
    {
        "url": "http://buchwurm.org",
        "ignoreUrl": ["/news-"]
    },
    { "url": "https://maaraavillosa.blogspot.de" },
    { "url": "http://www.ilovebooksblog.com" },
    { "url": "https://buechersindfliegendeteppiche.wordpress.com" },
    { "url": "https://zimttraeumereien.wordpress.com" },
    { "url": "http://ruthjusten.de" },
    { "url": "https://ninis-kleine-fluchten.blogspot.de" },
    { "url": "https://nik75.blogspot.de" },
    {
        "url": "http://www.lesertreff.net",
        "titleSelector": ".post h2"
    },
    { "url": "https://karthause.wordpress.com" },
    { "url": "http://das-buecherei.de" },
    { "url": "https://superlesehelden.com" },
    { "url": "https://sakuyasblog.blogspot.de" },
    { "url": "https://lus-buchgefluester.blogspot.de" },
    { "url": "https://shiku49.wordpress.com" },
    { "url": "https://elk-von-lyck.blogspot.de" },
    { "url": "https://jargsblog.wordpress.com" },
    { "url": "https://litoff.blogspot.de" },
    { "url": "https://funneswelt.blogspot.de" },
    {
        "url": "https://friedelchen.blogspot.de",
        "useFallbackDateFromUrl": true
    },
    { "url": "https://klusiliest.blogspot.de" },
    { "url": "https://meine-buecherwelt.blogspot.de" },
    { "url": "http://www.bookdibluempf.de" },
    {
        "url": "http://www.thefallingalice.de",
        "simulateBrowser": true
    },
    { "url": "https://simona1277.blogspot.de" },
    { "url": "http://www.nochmehrbuecher.de" },
    { "url": "https://tealiciousbooks.blogspot.de" },
    { "url": "https://durchleser.wordpress.com" },
    { "url": "http://bluebutterfly-buecherblog.de" },
    {
        "url": "http://www.am-lesestrand.de",
        "isArticlePagePattern": "(rezensionen/)",
        "titleSelector": ".article-bg h2",
        "articleSelector": ".article-bg"
    },
    { "url": "https://muffins-light-side.blogspot.de" },
    { "url": "https://schmoekereck.wordpress.com" },
    { "url": "https://literaturmaus.wordpress.com" },
    { "url": "http://lesevergnuegen-blog.de" },
    { "url": "https://martinabookaholic.wordpress.com" },
    { "url": "https://dierabenmutti.de" },
    { "url": "https://klingenfaenger.blogspot.de" },
    { "url": "http://www.schlunzenbuecher.de" },
    {
        "url": "https://teabooksandfairytales.blogspot.de",
        "useFallbackDateFromUrl": true
    },
    { "url": "https://thrillertante.blogspot.de" },
    {
        "url": "http://www.schattenwege.net",
        "titleSelector": ".content h2.title",
        "articleSelector": ".hentry"
    },
    { "url": "http://www.lost-pages.de" },
    { "url": "https://lesemaus87.blogspot.de" },
    { "url": "https://lillys-corner.blogspot.de" },
    { "url": "https://creativity-first.blogspot.de" },
    { "url": "https://seitenfetzer.wordpress.com" },
    { "url": "http://blog.geschichtenagentin.de" },
    { "url": "http://www.kulturpfleger.de" },
    {
        "url": "https://buchblinzler.blogspot.de",
        "simulateBrowser": true,
        "titleSelector": "h1.entry-title a",
        "dateSelector": ".publish-info",
        "articleSelector": ".entry-content"
    },
    { "url": "http://www.damarisliest.de" },
    { "url": "https://sophias-bookplanet.blogspot.de" },
    { "url": "https://twooks-twobooks.blogspot.de" },
    { "url": "https://mscaulfield.com" },
    { "url": "https://gerade-gelesen.blogspot.de" },
    { "url": "http://www.mybooksparadise.de" },
    { "url": "http://www.buecherwesen.de" },
    { "url": "https://fairy-book.blogspot.de" },
    { "url": "https://ladysbuecherwelten.blogspot.de" },
    { "url": "http://www.buecherinmeinerhand.ch" },
    { "url": "https://vanessas-buecherecke.blogspot.de" },
    { "url": "https://lesefee.blogspot.de" },
    { "url": "https://selenas-kreativlabor.blogspot.de" },
    { "url": "https://herzgeschichten.blogspot.de" },
    { "url": "https://angelikaliest.wordpress.com" },
    { "url": "https://bambinis-buecherzauber.blogspot.de" },
    { "url": "https://die-rezensentin.blogspot.de" },
    { "url": "https://buechersuechtig-sabine.blogspot.de" },
    { "url": "https://chrissisbuntelesecouch.wordpress.com" },
    { "url": "https://mordsbuecher.wordpress.com" },
    { "url": "https://lesemomente.net" },
    { "url": "http://www.dieleseentdecker.de" },
    { "url": "http://voellig-verlott.at" },
    { "url": "https://buecherwanderin.blogspot.de" },
    { "url": "https://neon-oati.blogspot.de" },
    { "url": "https://laesglaedje.wordpress.com" },
    { "url": "https://papierundtintenwelten.blogspot.de" },
    { "url": "http://buecherstadtkurier.com" },
    {
        "url": "https://wortgestalt-buchblog.de",
        "ignoreUrl": [ "?page_number" ]
    },
    { "url": "https://book-dreams.blogspot.de" },
    { "url": "https://booksandmore81.wordpress.com" },
    { "url": "http://www.seitenblicke-blog.de" },
    { "url": "https://lese-leuchtturm.de" },
    {
        "url": "https://woerterkatze.wordpress.com",
        "ignoreUrl": [ "in-365-" ]
    },
    { "url": "https://leckerekekse.de/wordpress/" },
    {
        "url": "http://www.biblometasia.de",
        "useFallbackDateFromUrl": true
    },
    { "url": "https://little-bookland.blogspot.de" },
    { "url": "https://dandelionliteratur.wordpress.com" },
    { "url": "https://zeilensprung-literatur-erleben.blogspot.de" },
    { "url": "https://geschichtenwolke.wordpress.com" },
    { "url": "https://lesemomente.blogspot.de" },
    { "url": "https://lesehunger.wordpress.com" },
    { "url": "https://tthinkttwice.wordpress.com" },
    {
        "url": "https://tintenhexe.blogspot.de",
        "titleSelector": ".entry-content h1",
        "useFallbackDateFromUrl": true
    },
    { "url": "https://claudiasbuecherhoehle.blogspot.de" },
    { "url": "https://lunasleseecke.blogspot.de" },
    { "url": "https://deepread.wordpress.com" },
    { "url": "https://golden-paperstories.blogspot.de" },
    {
        "url": "https://japanliteratur.net/",
        "titleSelector": ".grid62 h1",
        "articleSelector": ".wrapper div:nth-child(1)",
        "isArticlePageSelector": ".grid62 h1",
        "dateSelector": ".grid64"
    },
    { "url": "https://sanarkai-weltderbuecher.blogspot.de" },
    { "url": "https://natiswelt.de" },
    { "url": "http://lenaliest.de" },
    {
        "url": "https://zsadista.blogspot.de",
        "titleSelector": ".post-body div:nth-child(1)"
    },
    { "url": "https://everyones-a-book.blogspot.de" },
    { "url": "https://booksandbiscuit.blogspot.de" },
    { "url": "https://herrvoland.wordpress.com" },
    { "url": "http://books-and-cats.de" },
    { "url": "https://bibliophiline.wordpress.com" },
    { "url": "https://thecalloffreedomandlove.blogspot.de" },
    { "url": "https://kinderbibliothek.blogspot.de" },
    { "url": "https://astishexenwerk.blogspot.de" },
    { "url": "https://lesenmachtgluecklich.wordpress.com" },
    { "url": "http://www.xn--bcherblogger-dlb.com/" },
    { "url": "http://www.readingpenguin.de" },
    { "url": "https://cat-buecher-welt.blogspot.de" },
    { "url": "http://leseratteffm.de" },
    { "url": "https://schnuffelchensbuecher.blogspot.de" },
    {  "url": "https://lesendes-katzenpersonal.blogspot.de" },
    { "url": "http://www.booksonfire.de" },
    { "url": "https://literaturjunkie.wordpress.com" },
    { "url": "https://skyline-of-books.blogspot.de" },
    { "url": "https://buecherblumen.blogspot.de" },
    { "url": "https://www.seitenhain.de" },
    { "url": "https://seitengang.wordpress.com" },
    {
        "url": "https://atomicleonie.blogspot.de",
        "titleSelector": ".post-title-container .post-title"
    },
    { "url": "https://lesegenuss.blogspot.de" },
    { "url": "https://buchtraumwelten.blogspot.de" },
    { "url": "https://www.lesezeit-blog.de" },
    { "url": "https://claudes-schatzkiste.blogspot.de" },
    { "url": "http://www.daggis-welt.de" },
    { "url": "https://kleeblatts-buecherblog.blogspot.de" },
    { "url": "https://sputnikffm.wordpress.com/" },
    { "url": "https://buntebuecherwelt.blogspot.de" },
    { "url": "http://www.favolas-lesestoff.ch" },
    { "url": "http://influenza-bookosa.de" },
    {
        "url": "https://carolgrayson-darkromance.blogspot.de",
        "simulateBrowser": true,
        "titleSelector": "h1.entry-title a",
        "dateSelector": ".publish-info",
        "articleSelector": ".entry-content"
    },
    { "url": "https://thelostartofkeepingsecrets.wordpress.com" },
    { "url": "https://anna-buecher.blogspot.de" },
    { "url": "https://nothingbutn9erz.blogspot.de" },
    { "url": "https://litterae-artesque.blogspot.de" },
    { "url": "https://www.schmetterlingsliteraturreise.de" },
    {
        "url": "http://www.hoerbuchecke.eu",
        "feed": "https://hoerbuchecke.blogspot.de/feeds/posts/default",
        "frame": "https://hoerbuchecke.blogspot.de",
        "titleSelector": ".post_title a:nth-child(2)"

    },
    { "url": "https://monerls-bunte-welt.blogspot.de" },
    { "url": "https://buchwellenreiter.blogspot.de" },
    { "url": "https://wolfgangschiffer.wordpress.com" },
    { "url": "https://niliversum.wordpress.com" },
    {
        "url": "https://sarahsbuecherhoehle.blogspot.de",
        "useFallbackDateFromUrl": true
    },
    { "url": "https://nickisbuecherwelt.blogspot.de" },
    {
        "url": "http://www.ebooksofa.de",
        "feed": "http://www.ebooksofa.bgp24.eu/blog/feed/",
        "frame": "http://www.ebooksofa.bgp24.eu/blog"
    },
    { "url": "https://aigantaigh.wordpress.com" },
    { "url": "http://literaturliebe.de/" },
    {
        "url": "https://palomapixel.blogspot.de",
        "titleSelector": ".post-title h1"
    },
    { "url": "https://dreamcatchers-rezensionen.blogspot.de" },
    {
        "url": "https://book-angel.blogspot.de",
        "useFallbackDateFromUrl": true
    },
    { "url": "https://franzyliestundlebt.blogspot.de" },
    { "url": "https://leniliest.blogspot.de" },
    { "url": "http://inkofbooks.com" },
    { "url": "http://book-walk.de" },
    { "url": "https://luiline.blogspot.de" },
    { "url": "https://myworldfullofbooks.blogspot.de" },
    { "url": "https://skjoonsbuecher.blogspot.de" },
    { "url": "https://jekranta.jimdo.com" },
    { "url": "https://www.book-cats.com" },
    { "url": "https://lesen-ist-sexy.blogspot.de" },
    { "url": "https://book-blossom.blogspot.de" },
    { "url": "https://donatasbuecher.blogspot.de" },
    {
        "url": "https://wonderworld-of-books-from-hannah.blogspot.de",
        "useFallbackDateFromUrl": true
    },
    { "url": "https://goldkindchen.blogspot.de" },
    { "url": "https://kleinbrina.wordpress.com" },
    { "url": "http://www.eulengewisper.de" },
    { "url": "https://prowling-books.blogspot.de" },
    {
        "url": "https://immer-mit-buch.blogspot.de",
        "titleSelector": ".post h3.post-title.entry-title"
    },
    { "url": "https://irveliest.wordpress.com" },
    { "url": "http://yviswelt.de" },
    { "url": "https://traumfantasiewelten.blogspot.de" },
    { "url": "https://uwes-leselounge.blogspot.de" },
    { "url": "https://bessis-louisiana.blogspot.de" },
    { "url": "https://nettebuecherkiste.wordpress.com" },
    { "url": "https://booksaretrueadventures.blogspot.de" },
    { "url": "https://aletheias-welt.blogspot.de" },
    { "url": "https://www.booknerds.de" },
    { "url": "https://dramaslesetipps.blogspot.de" },
    {
        "url": "https://minicaspi-bucherwelt.blogspot.de",
        "titleSelector": ".post h3.post-title.entry-title"
    },
    { "url": "http://www.enchantedbooks.de" },
    { "url": "https://nichtnocheinbeautyblog.blogspot.de" },
    { "url": "https://nadys-buecherwelt.jimdo.com" },
    { "url": "https://i-am-bookish.blogspot.de" },
    { "url": "https://bucheckle.blogspot.de" },
    { "url": "http://wunderliteratur.de" },
    { "url": "https://lesemappe.blogspot.de" },
    { "url": "https://buchstabenfestival.blogspot.de" },
    { "url": "https://magischemomentefuermich.blogspot.de" },
    {
        "url": "https://jasondawn-luxaeterna.blogspot.de",
        "simulateBrowser": true,
        "titleSelector": "h1.entry-title a",
        "dateSelector": ".publish-info",
        "articleSelector": ".entry-content"
    },
    { "url": "https://booklove-bloggt.blogspot.de" },
    { "url": "https://buch-fresserchen.blogspot.de" },
    { "url": "https://spiegelseelen.blogspot.de" },
    { "url": "https://themis100000buecher.blogspot.de" },
    { "url": "https://diedunklenfelle.wordpress.com" },
    { "url": "http://reading-books.de" },
    { "url": "https://sasija.blogspot.de" },
    { "url": "https://tinaskleinebuecherwelt.blogspot.de" },
    { "url": "https://liveyourlifewithbooks.wordpress.com" },
    {
        "url": "http://www.kastanies-leseecke.de",
        "titleSelector": "h1.storytitle",
        "articleSelector": ".storycontent"
    },
    { "url": "https://fraeulein-eule.blogspot.de" },
    { "url": "https://wallis-buechersichten.blogspot.de" },
    { "url": "https://buecherstuff.blogspot.de" },
    { "url": "https://janine2610.blogspot.de" },
    { "url": "https://traeumenvonbuechern.blogspot.de" },
    { "url": "https://querbeetlesen.blogspot.de" },
    {
        "url": "http://www.buchtempel.net",
        "feed": "https://glitzerfees.blogspot.de/feeds/posts/default",
        "frame": "https://glitzerfees.blogspot.de"
    },
    { "url": "https://buchundliteratur.blogspot.de" },
    {
        "url": "https://tausendbuecher.blogspot.de",
        "useFallbackDateFromUrl": true
    },
    {
        "url": "http://www.kerstins-reich.de/buecherreich/",
        "isArticlePagePattern": "/?p=",
        "dateSelector": ".beitragsfuss",
        "titleSelector": ".beitragskopf"
    },
    { "url": "https://buchrezensionen-nazurka.blogspot.de" },
    { "url": "https://dragonsbookworld.blogspot.de" },
    { "url": "https://sternchenstaubs-lesewelt.blogspot.de" },
    { "url": "https://bellezza-ribelle.blogspot.de" },
    { "url": "https://notizhefte.com" },
    { "url": "https://jennybuecher.blogspot.de" },
    { "url": "https://buechergnomen.wordpress.com" },
    { "url": "https://masuko13.wordpress.com" },
    { "url": "https://leseschatz.com" },
    { "url": "http://www.buechersalat.de" },
    { "url": "https://booknaerrisch.blogspot.de" },
    { "url": "https://www.rezensionaer.de" },
    { "url": "https://keinezeitfuerlangeweile.blogspot.de" },
    {
        "url": "https://durchgebloggt.blogspot.de",
        "useFallbackDateFromUrl": true
    },
    { "url": "http://www.buecher-bloggeria.de" },
    { "url": "http://www.bornfromthesky.de" },
    {
        "url": "http://www.beckysworldofbooks.de",
        "titleSelector": ".entry-intro h1"
    },
    { "url": "http://analogzweinull.de" },
    {
        "url": "https://phantastikon.de",
        "ignoreDate": true
    },
    { "url": "https://sternelandzauber.blogspot.de" },
    { "url": "https://johannisbeerchens-buecher.blogspot.de" },
    { "url": "https://nenyas-book-wunderland.blogspot.de" },
    { "url": "https://elasbookinette.wordpress.com" },
    { "url": "https://studierenichtdeinleben.wordpress.com" },
    { "url": "https://traumbuchfaenger.blogspot.de" },
    { "url": "http://www.drachenleben.de" },
    { "url": "https://bucherdiebin.blogspot.de" },
    { "url": "https://daughterofinkandpaper.blogspot.de/" },
    { "url": "https://amerdale.wordpress.com" },
    { "url": "https://merlinsbuecher.blogspot.de" },
    { "url": "https://book-addicted.blogspot.de" },
    { "url": "https://wortwucher.blogspot.de" },
    { "url": "https://lesenlieben.wordpress.com" },
    { "url": "https://thebookpassion.blogspot.de" },
    { "url": "https://abendsternchen.blogspot.de" },
    { "url": "https://melbuecherwurm.blogspot.de" },
    {
        "url": "https://bluubsbuecherwelt.blogspot.de",
        "titleSelector": ".post h3.post-title.entry-title"
    },
    { "url": "https://booksofdandelion.blogspot.de/" },
    { "url": "https://missnaseweisblog.wordpress.com" },
    { "url": "https://elchisworldofbooks.blogspot.de" },
    { "url": "https://booknaator.blogspot.de" },
    { "url": "https://amezaliwa.blogspot.de" },
    { "url": "https://erlesenebuecher.wordpress.com" },
    { "url": "https://anjasbuecher.blogspot.de" },
    { "url": "https://manustintenkleckse.blogspot.de" },
    { "url": "https://intheprimetimeoflife.blogspot.de" },
    { "url": "http://moment-aufnahme.net" },
    {
        "url": "https://lese-himmel.blogspot.de",
        "isArticlePageSelector": ".post"
    },
    {
        "url": "https://httpxeniana.com",
        "titleSelector": "header.entry-header h1.entry-title"
    },
    { "url": "https://laetitia-koenkamp.blogspot.de" },
    { "url": "https://teriisbuecherblog.blogspot.de" },
    { "url": "https://tayachanlovesalisu.blogspot.de" },
    {
        "url": "http://infinitybooks.de",
        "titleSelector": ".post h1.art-postheader.entry-title",
        "articleSelector": "article.post"
    },
    { "url": "https://www.buchflimmern.de" },
    { "url": "https://buecherwiediese.blogspot.de" },
    { "url": "http://www.liberiarium.de" },
    { "url": "https://buchbewertungen.blogspot.de" },
    { "url": "https://fjolamausis-leseecke.blogspot.de" },
    { "url": "https://nine-im-wahn.blogspot.de" },
    { "url": "https://steffis-und-heikes-lesezauber.blogspot.de" },
    { "url": "https://colliding-worlds.blogspot.de" },
    { "url": "https://eclipses-buecherregal.blogspot.de" },
    { "url": "https://dreaming-till-midnight.blogspot.de" },
    { "url": "https://feuerflocken.wordpress.com" },
    {
        "url": "http://schlummerfrosch.de",
        "dateSelector": ".postmetadata",
        "titleSelector": ".post h2",
        "articleSelector": ".entry"
    },
    {
        "url": "https://nico-wallmann.blogspot.de",
        "useFallbackDateFromUrl": true
    },
    { "url": "https://sunsys-blog.blogspot.de/" },
    { "url": "https://zeilensehnsucht.blogspot.de" },
    { "url": "https://jennys-buecherkiste.blogspot.de" },
    { "url": "https://anruba.blogspot.de" },
    { "url": "https://lasszeilensprechen.blogspot.de" },
    { "url": "https://buchstuetze.wordpress.com" },
    { "url": "https://buecherrezension.com" },
    { "url": "https://secrets-of-nobody.blogspot.de" },
    { "url": "https://betty-schmidt.blogspot.de" },
    { "url": "https://hoerbuchecke.blogspot.de" },
    { "url": "https://jacquysthoughts.blogspot.de" },
    { "url": "https://carasbuecherwahn.blogspot.de", "feed": "https://www.blogger.com/feeds/7644302988189992654/posts/default" },
    { "url": "https://literaturaustausch.blogspot.de" },
    { "url": "https://svenjasbookchallenge.blogspot.de" },
    { "url": "https://buecherunddiewelt.wordpress.com" },
    { "url": "https://kaddesschmoeker.wordpress.com" },
    { "url": "https://sarah-liest.blogspot.de" },
    { "url": "https://goood-reading.blogspot.de" },
    { "url": "https://tjskleinebuecherwelt.blogspot.de" },
    { "url": "https://glitzerfees.blogspot.de" },
    { "url": "http://bibilotta.de" },
    { "url": "http://www.leseliebe.blog" },
    { "url": "https://buecherparadiesx3.blogspot.de" },
    { "url": "https://magicallyprincess.blogspot.de" },
    { "url": "https://worldwidebookz.blogspot.de" },
    { "url": "https://josiajourdan.ch/wordpress" },
    { "url": "http://nadines-lesewelt.de" },
    { "url": "https://dhiammara.blogspot.de" },
    { "url": "https://books-are-fantastic.blogspot.de" },
    { "url": "https://in-buechern-leben.blogspot.de" },
    { "url": "https://leseratte1969.blogspot.de" },
    { "url": "http://wiewerdenwirlesen.de" },
    { "url": "http://buchblog.schreibtrieb.com" },
    { "url": "https://lynes-books.blogspot.de" },
    { "url": "https://buecher-newswelt.blogspot.de" },
    { "url": "https://buchbooks.blogspot.de" },
    { "url": "https://lillisbuchseite.wordpress.com" },
    { "url": "https://nicis-buchecke.blogspot.de" },
    { "url": "http://buch-haltung.com" },
    { "url": "https://monasbuecher.blogspot.de" },
    { "url": "https://zauberhaftebuecherwelt.blogspot.de" },
    { "url": "http://www.sasverse.de" },
    { "url": "http://www.buchimpressionen.de" },
    {
        "url": "https://postmondaen.net",
        "simulateBrowser": true
    },
    {
        "url": "https://readingbookpauli.blogspot.de",
        "simulateBrowser": true,
        "titleSelector": ".entry-content div:nth-child(1)",
        "dateSelector": ".publish-info",
        "articleSelector": ".entry-content"
    },
    { "url": "http://www.foxybooks.de" },
    { "url": "https://a-bookdemon.blogspot.de" },
    { "url": "https://reading-parrot.blogspot.de" },
    {
        "url": "https://fascinating-books.blogspot.de",
        "articleSelector": "article",
        "titleSelector": "article h2"
    },
    { "url": "https://literatouristin.org" },
    { "url": "https://phinchensfantasyroom.blogspot.de" },
    { "url": "https://lielan-reads.blogspot.de" },
    { "url": "https://dieinsieule.blogspot.de" },
    { "url": "https://einanfangundkeinende.wordpress.com" },
    { "url": "https://lenasbuechertraum.blogspot.de" },
    { "url": "https://tulpentopf.de" },
    { "url": "https://zeichenundzeiten.com" },
    { "url": "https://vanessasbuecherecke.wordpress.com" },
    { "url": "http://lesefreude.at" },
    { "url": "http://www.herzenszeilen.de" },
    { "url": "https://buechergoere.wordpress.com" },
    { "url": "http://www.lesensiegut.de" },
    { "url": "https://privatliteratur.wordpress.com" },
    { "url": "https://foodmeetsbooks.blogspot.de" },
    { "url": "https://marinasbuecherwelt.blogspot.de" },
    { "url": "https://vanniis-book-paradise.blogspot.de" },
    { "url": "https://annaskleinebuecherwelt.blogspot.de" },
    {
        "url": "http://www.wortmalerei.org",
        "useFallbackDateFromUrl": true
    },
    { "url": "https://buchzeiten.blogspot.de" },
    { "url": "http://stehlblueten.de" },
    { "url": "https://allysbooksession.blogspot.de" },
    { "url": "https://nicolesbuecherwelt.blogspot.de" },
    { "url": "https://schiefgelesen.net" },
    { "url": "https://diogenesclubbing.wordpress.com" },
    { "url": "https://buecherprinzessin.wordpress.com" },
    { "url": "https://mylovelybooksblog.wordpress.com" },
    { "url": "https://read-dream-fall.blogspot.de" },
    { "url": "http://www.kathleens-buecherwelt.de" },
    { "url": "https://lizoyfanes.blogspot.de" },
    { "url": "https://www.mordsbuch.net" },
    { "url": "https://traumweltlesen.blogspot.de" },
    { "url": "https://buchpost.blogspot.de" },
    { "url": "https://booklvestory.blogspot.de" },
    { "url": "http://www.buecherchamaeleon.de" },
    { "url": "https://liviliest.blogspot.de" },
    { "url": "http://www.nanawhatelse.at" },
    { "url": "https://tattooedtree.blogspot.de" },
    { "url": "https://wasliestlisa.blogspot.de" },
    { "url": "https://books-my-first-love.blogspot.de" },
    { "url": "https://bibliotaphblog.wordpress.com" },
    { "url": "https://buecherwelt-auf-samtpfoten.blogspot.de" },
    { "url": "https://buchstabentraeumerei.wordpress.com" },
    { "url": "http://www.elkes-literaturwolke.de" },
    {
        "url": "http://paradoxes-leben.de",
        "removeSelector": [".gossipblog_posts_type_widget"]
    },
    { "url": "https://sarahs-buecherregal.blogspot.de" },
    { "url": "https://buecherherbst.wordpress.com" },
    { "url": "https://liebezwischendenzeilen.blogspot.de" },
    { "url": "https://hoernchensbuechernest.blogspot.de" },
    { "url": "http://buchlotsin.de" },
    { "url": "https://sternenbrise.wordpress.com" },
    { "url": "https://marissaconrady.blogspot.de" },
    {
        "url": "https://buchmomente.blogspot.de",
        "simulateBrowser": true
    },
    { "url": "https://fantasyblogger.wordpress.com" },
    { "url": "https://melanies-buecherwelt.blogspot.de" },
    { "url": "https://www.literaturlounge.eu" },
    { "url": "https://windsprecher.blogspot.de" },
    { "url": "https://janines-leselounge.blogspot.de" },
    { "url": "http://www.fuchsiasweltenecho.de" },
    { "url": "https://booksaweek.blogspot.de" },
    {
        "url": "https://www.lottis-kinder.com",
        "isArticlePageSelector": ".j-blog-post--date"
    },
    { "url": "http://www.buchwelt.co.at" },
    { "url": "https://fantasie-und-traeumerei.blogspot.de" },
    { "url": "https://book-up-your-life.blogspot.de" },
    { "url": "https://buchverliebt.blogspot.de" },
    { "url": "https://likeagaydream.wordpress.com" },
    { "url": "https://mirisbookworld.blogspot.de" },
    { "url": "http://www.angeltearz-liest.de" },
    { "url": "http://www.meinbuchmeinewelt.de" },
    { "url": "https://buchherz.blog" },
    { "url": "https://tapsisbuchblog.blogspot.de" },
    { "url": "https://kiyaliest.wordpress.com" },
    { "url": "http://zeit-zu-lesen.de" },
    {
        "url": "https://lese-madeleines.blogspot.de",
        "titleSelector": ".entry-content div:nth-child(1)"
    },
    { "url": "https://mybookstagram.blogspot.de" },
    { "url": "https://lisasbuechereck.blogspot.de" },
    { "url": "https://marcysbuecherecke.blogspot.de" },
    {
        "url": "http://www.wortmax.de",
        "removeSelector": [".tabs-widget-wrapper"]
    },
    { "url": "https://dufttrunken.blogspot.de" },
    {
        "url": "https://julianafabula.blogspot.de",
        "useFallbackDateFromUrl": true
    },
    { "url": "https://marys-buecherwelten.blogspot.de" },
    { "url": "https://lesemanie.com" },
    { "url": "https://avareed.blogspot.de" },
    {
        "url": "http://diary-of-a-booklover.tumblr.com",
        "isArticlePagePattern": "(post/)",
        "titleSelector": ".article-title",
        "articleSelector": "article",
        "dateSelector": "script"
    },
    { "url": "https://myreadingpalace.blogspot.de" },
    { "url": "https://neyasha.blogspot.de" },
    { "url": "https://libriabella.wordpress.com" },
    { "url": "http://timeandtea.de" },
    { "url": "https://charleenstraumbibliothek.blogspot.de" },
    { "url": "https://buchliebebykerstin.blogspot.de" },
    {
        "url": "https://lifewithsaskia.blog",
        "titleSelector": ".postarea h1.headline",
        "articleSelector": ".postarea",
        "removeSelector": ["#comments"]
    },
    { "url": "https://kunterbuntestagebuch.com" },
    { "url": "https://buecherstoeberecke.blogspot.de" },
    { "url": "http://annasbuecherstapel.de" },
    { "url": "https://crazyforbooksdotnet.blogspot.de" },
    { "url": "https://buchinderhand.com" },
    { "url": "https://booksinvienna.wordpress.com" },
    { "url": "http://www.nicoleliest.com" },
    { "url": "https://julesleseecke.wordpress.com" },
    { "url": "https://isasbuecherregal.wordpress.com" },
    { "url": "https://armariumnostrum.wordpress.com" },
    { "url": "https://knbooksobsession.blogspot.de" },
    { "url": "https://mylifewithbooks5.blogspot.de" },
    { "url": "https://mariesbuecher.blogspot.de" },
    { "url": "https://leseengelsblog.blogspot.de" },
    { "url": "https://leuchtturmwaerterin.blogspot.de" },
    { "url": "https://selectionbooks.blogspot.de" },
    { "url": "https://buchlese.wordpress.com" },
    { "url": "https://buchkuschler.blogspot.de" },
    { "url": "https://laurasbookdiary.blogspot.de" },
    { "url": "https://hannahs-world-of-books.jimdo.com" },
    { "url": "http://booksdream.de/Blog" },
    { "url": "https://kathis-buecherecke.blogspot.de" },
    { "url": "https://fionafabelhaft.blogspot.de/" },
    { "url": "https://sophies-little-book-corner.blogspot.de" },
    { "url": "https://miisbuecherwelt.blogspot.de" },
    { "url": "https://lovin-books.de" },
    { "url": "https://leseseiten.wordpress.com" },
    { "url": "https://tamysbuecherwelt.wordpress.com" },
    { "url": "https://natiraszeit.blogspot.de" },
    {
        "url": "https://read-feel-love.blogspot.de",
        "useFallbackDateFromUrl": true
    },
    { "url": "https://bookwonderlandc.blogspot.de" },
    { "url": "https://78sunny.blogspot.de" },
    { "url": "https://buecherunserleben.blogspot.de" },
    { "url": "https://diebuchblogger.wordpress.com" },
    { "url": "https://letannasblog.blogspot.de" },
    { "url": "https://buchmagie88.blogspot.de" },
    { "url": "https://the-infinite-bookshelf.blogspot.de" },
    { "url": "https://buchmagie.de" },
    { "url": "https://juliliest.net" },
    { "url": "https://zauberhaftebuecherwelt2016.blogspot.de" },
    { "url": "https://binzis-buecher.blogspot.de" },
    { "url": "https://linas-buechertraumwelt.blogspot.de" },
    { "url": "https://mexiis-leseparadies.blogspot.de" },
    { "url": "http://www.bellas-life.de" },
    { "url": "https://letusreadsomebooks.com" },
    { "url": "http://www.meinebuecherkueche.de" },
    {
        "url": "http://gretchenfrage.org",
        "titleSelector": ".post-title.post-el.single-title"
    },
    { "url": "https://buecherduft.blogspot.de" },
    { "url": "http://www.zwinkerlingsbibliothek.de" },
    { "url": "https://angisbuecherkiste.blogspot.de" },
    { "url": "https://jennysbuecherkiste.blogspot.de" },
    { "url": "https://library-of-fairytales.blogspot.de" },
    { "url": "https://fraeuleinlovingbooks.wordpress.com" },
    { "url": "https://resas-welt.blogspot.de" },
    {
        "url": "https://sophie-bookdiary.blogspot.de",
        "titleSelector": "article h3.post-title.entry-title"
    },
    { "url": "https://tinyhedgehog.blogspot.de" },
    { "url": "http://hannifuchs.de" },
    { "url": "https://seelenlesezeichen.blogspot.de" },
    { "url": "https://twineetys-lesereise.blogspot.de" },
    { "url": "https://buecherjase.wordpress.com" },
    { "url": "https://buchaviso.de" },
    { "url": "https://seitenliebe.blogspot.de" },
    { "url": "https://meinlebenvollerbuecher.blogspot.de" },
    { "url": "https://eliscoffeebreak.blogspot.de" },
    { "url": "https://winterkatzesbuchblog.blogspot.de" },
    { "url": "https://meinbuechertagebuch.wordpress.com" },
    { "url": "https://luisasbuecherliebe.blogspot.de" },
    { "url": "https://buchstabengefluester.blogspot.de" },
    {
        "url": "https://literaturchaos.jimdo.com",
        "isArticlePagePattern": "(rezensionen/)",
        "ignoreDate": true
    },
    { "url": "https://perolicious.blogspot.de" },
    { "url": "http://www.buchsichten.de" },
    { "url": "https://derbuchblog.com" },
    { "url": "https://seductivebooks.blogspot.de" },
    { "url": "https://inasbuecherkiste.blogspot.de" },
    { "url": "https://nalalayoc.blogspot.de" },
    {
      "url": "https://literameer.blogspot.de",
      "useFallbackDateFromUrl": true
    },
    { "url": "https://buecherherz.wordpress.com" },
    { "url": "https://buecherfunke.blogspot.de" },
    { "url": "https://linasbuecher.blogspot.de" },
    { "url": "http://www.cookbakebook.de" },
    { "url": "https://kruemelchenundseinefreunde.wordpress.com" },
    { "url": "https://theloyalme.blogspot.de" },
    { "url": "https://seitenwinde.wordpress.com" },
    { "url": "https://dieseitenfluesterer-unserbuchblog.blogspot.de" },
    { "url": "https://passion4books.de", "feed": "https://passion4books.de/feed/" },
    { "url": "https://katrinslesewelt.blogspot.de" },
    {
        "url": "https://sasapull.wordpress.com",
        "isArticlePagePattern": "(buchvorstellungen/)"
    },
    { "url": "https://zwischendenseiten.wordpress.com" },
    { "url": "http://binesblogs.de" },
    { "url": "https://ltrtr.wordpress.com" },
    { "url": "https://der-duft-von-buechern-und-kaffee.blogspot.de" },
    {
        "url": "https://beckysdiner.wordpress.com",
        "titleSelector": "h1.single-title"
    },
    { "url": "https://buecherfantasien.blogspot.de" },
    { "url": "http://www.xn--bcherschtiges-herz-m6bf.de" },
    { "url": "https://frauhollestoechter.blogspot.de" },
    { "url": "https://bettysbuecherweeelt.blogspot.de" },
    { "url": "https://lost-in-written-words.blogspot.de" },
    { "url": "https://piasbuecherparadies.blogspot.de" },
    { "url": "https://buchding.com" },
    { "url": "https://lullabys-buecherkiste.blogspot.de" },
    { "url": "https://buchimblick.blogspot.de" },
    { "url": "https://tesbuecherblog.blogspot.de" },
    { "url": "https://lilly-lilith.blogspot.de" },
    { "url": "https://loraliest.blogspot.de" },
    { "url": "https://elizasbuecherparadies.wordpress.com" },
    { "url": "https://sternenstaubbuchblog.blogspot.de" },
    { "url": "https://annikasbookwonderland.blogspot.de" },
    { "url": "https://kopfkino-blog.blogspot.de" },
    { "url": "https://herrbooknerd.blogspot.de" },
    { "url": "https://lesekatzen.blogspot.de" },
    { "url": "http://www.buecherwurmloch.at" },
    { "url": "https://buch-leben.blogspot.de" },
    { "url": "https://pagesingold.wordpress.com" },
    { "url": "https://marens-buecherkiste.blogspot.de" },
    { "url": "https://ge-h-schichten.blogspot.de" },
    { "url": "https://leselustich.com" },
    { "url": "https://irisworldofbooks.wordpress.com" },
    { "url": "https://papierschmetterling.wordpress.com" },
    { "url": "https://buecherblase.blogspot.de" },
    { "url": "https://kumosbuchwolke.blogspot.de" },
    { "url": "https://booksnstories.wordpress.com" },
    { "url": "http://schreiblust-leselust.de" },
    { "url": "https://dagmar-blog.blogspot.de" },
    { "url": "http://www.corinnasworldofbooks.de" },
    { "url": "https://catas-welt.blogspot.de" },
    { "url": "https://miss-page-turner.blogspot.de" },
    { "url": "https://buecherbewertungen1.blogspot.de" },
    { "url": "http://buecherheldin.de" },
    {
        "url": "http://www.poriomaniacs.de",
        "frame": "https://deniseyokoberndt.blogspot.de"
    },
    { "url": "https://buecherschmoeker.com" },
    { "url": "http://www.bettinalippenberger.de" },
    { "url": "https://ruby-celtic-testet.blogspot.de" },
    { "url": "https://mihas-channel.blogspot.de" },
    { "url": "https://worldofbooksanddreams.blogspot.de" },
    { "url": "https://zeilenverliebt.blogspot.de" },
    { "url": "https://rezensionenmitherz.blogspot.de" },
    { "url": "https://wissenstagebuch.com" },
    { "url": "https://claudiabett.com" },
    { "url": "https://the-bookwonderland.blogspot.de" },
    { "url": "https://morticiashellbooks.blogspot.de" },
    { "url": "http://www.26stories.de" },
    { "url": "http://poesierausch.com" },
    { "url": "https://ulla-liebt-buecher.blogspot.de" },
    {
        "url": "http://pinkfisch.net",
        "titleSelector": "h1.entry-title"
    },
    { "url": "https://phantastisch-lesen.com" },
    { "url": "https://angeliquesbuecherblog.blogspot.de" },
    { "url": "https://meikeslittleworldofbooks.blogspot.de" },
    { "url": "https://tantetex.wordpress.com" },
    { "url": "https://weltentaucherblog.wordpress.com" },
    {
        "url": "https://pergamentfalter.blogspot.de",
        "dateSelector": ".post-header"
    },
    { "url": "http://nicoles-fantasy.de" },
    { "url": "https://sarahsbuecherliebe.blogspot.de" },
    { "url": "https://thebookstorys.blogspot.de" },
    { "url": "https://sommerlese.blogspot.de" },
    { "url": "https://bibliophilias-buecherhimmel.blogspot.de" },
    { "url": "http://kinderbuch-detektive.de" },
    { "url": "http://tinas-buch-rezensionen.de" },
    { "url": "https://selene-niniel.blogspot.de" },
    { "url": "https://literatenwelt.blogspot.de" },
    { "url": "https://meinbuecherzimmer.blogspot.de" },
    { "url": "https://kristinas-lesewelt.de" },
    { "url": "https://storyline2412.blogspot.de" },
    { "url": "https://mycharmingbooks.blogspot.de" },
    { "url": "https://novellieren.com" },
    { "url": "https://anjafrieda.blogspot.de" },
    { "url": "https://dailythoughtsofbooks.wordpress.com" },
    { "url": "https://nomasliteraturblog.wordpress.com" },
    { "url": "https://nicoles-bibliothek.de" },
    {
        "url": "https://missmesmerized.wordpress.com",
        "titleSelector": "header.entry-header h1.entry-title"
    },
    { "url": "https://book-nerd1310.blogspot.de" },
    { "url": "https://anduriarecca.wordpress.com" },
    { "url": "http://blog.fiks.de" },
    { "url": "https://missnorges.blogspot.de" },
    { "url": "https://mirella-pagnozzi.blogspot.de" },
    { "url": "https://buch-ninja.de" },
    { "url": "http://www.favolinajunior.ch" },
    { "url": "https://hundstrueffel.wordpress.com" },
    { "url": "https://buecherliebe-mone.blogspot.de" },
    { "url": "https://www.tinte-und-schwert.de" },
    { "url": "https://bibliomanie2.blogspot.de" },
    { "url": "https://fantasybooks-shadowtouch.blogspot.de" },
    { "url": "https://litis-fabelhafte-welt-der-buecher.blogspot.de" },
    { "url": "http://tinaliestvor.de" },
    { "url": "https://rudkoffsky.com" },
    { "url": "https://lagoonadelmar.wordpress.com" },
    { "url": "https://buecherdiebe.blogspot.de" },
    { "url": "https://herbstmosaik.blogspot.de" },
    { "url": "https://papillionisliest.wordpress.com" },
    { "url": "https://levenyasbuchzeit.blogspot.de" },
    { "url": "https://wortesammlerin.wordpress.com" },
    { "url": "https://apathy-lovebooks.blogspot.de" },
    { "url": "https://pinoca.blogspot.de" },
    { "url": "https://laberladen.com" },
    { "url": "https://leserattenhoehle.blogspot.de" },
    { "url": "https://familieimchaos.blogspot.de" },
    { "url": "https://buechersindfreunde.blogspot.de" },
    { "url": "https://silencesbuecherwelt.blogspot.de" },
    { "url": "https://geschichten-liebe.blogspot.de" },
    { "url": "https://time-for-nele.blogspot.de" },
    { "url": "https://buechertaenzerin.blogspot.de" },
    {
      "url": "https://happybooktime.blogspot.de",
      "useFallbackDateFromUrl": true
    },
    { "url": "https://fraunatbooks.wordpress.com" },
    { "url": "https://welivedathousandlifes.wordpress.com" },
    {
        "url": "http://tausendleben.de",
        "isArticlePageSelector": "body.singular"
    },
    { "url": "http://revolutionbabyrevolution.de" },
    { "url": "https://buchstabenliebeblog.wordpress.com" },
    { "url": "https://krimilese.wordpress.com" },
    { "url": "https://alicebuch.blogspot.de" },
    { "url": "https://wabuwabui.blogspot.de" },
    { "url": "https://yunikas-buecherwelt.blogspot.de" },
    { "url": "https://stuffed-shelves.de" },
    { "url": "http://trooboox.de/wordpress/" },
    { "url": "http://du-bist-was-du-liest.de" },
    { "url": "https://literaturgefluester.wordpress.com" },
    { "url": "https://leselebenszeichen.wordpress.com" },
    { "url": "https://krimirezensionen.wordpress.com" },
    { "url": "https://zeit-fuer-neue-genres.blogspot.de" },
    { "url": "https://tianas-buecherfeder.blogspot.de" },
    { "url": "https://fluesterndewortebuecherblog.blogspot.de" },
    { "url": "http://wortlichter.com" },
    {
        "url": "https://written-between-the-lines.blogspot.de",
        "simulateBrowser": true
    },
    { "url": "https://letteraturablog.wordpress.com" },
    { "url": "https://www.walk-the-lines.de" },
    { "url": "https://lionsandwitches.wordpress.com" },
    { "url": "https://littlecornerformybooks.blogspot.de" },
    { "url": "http://www.buchlieblinge.de" },
    { "url": "https://teeniebookblog.wordpress.com" },
    { "url": "https://einlesehorn.com" },
    { "url": "https://thebluesirenblog.wordpress.com" },
    {
        "url": "http://www.bookstorm.de",
        "titleSelector": "h1.entry-title"
    },
    { "url": "https://thewonderlandbooks.wordpress.com" },
    { "url": "http://buecherratten.at" },
    { "url": "https://lovinbooksworld.blogspot.de" },
    { "url": "https://seistillsieliest.blogspot.de" },
    {
        "url": "http://schwarzaufweiss.online",
        "simulateBrowser": true
    },
    { "url": "https://valaraucos-buchstabenmeer.com" },
    { "url": "https://denkzeiten.com" },
    { "url": "https://awkward-dangos.blogspot.de" },
    {
        "url": "https://beneaboutbooks.blogspot.de",
        "titleSelector": ".post-body div:nth-child(1)"
    },
    { "url": "https://lizasbuecherwelt.wordpress.com" },
    { "url": "https://bookaddiction99.blogspot.de" },
    { "url": "https://mimisleseecke.wordpress.com" },
    { "url": "https://buchundmedienblog.com" },
    { "url": "https://crashies-wonderland.blogspot.de" },
    { "url": "https://blackfairys-buecher.blogspot.de" },
    { "url": "https://wolfgangschnier.com" },
    { "url": "http://www.protagonistplaces.de" },
    {
        "url": "https://buecherfeder.blogspot.de",
        "titleSelector": ".post h3.post-title.entry-title"
    },
    { "url": "https://derschneemann.net" },
    { "url": "https://buchgefuehl.blogspot.de" },
    { "url": "https://alisiaswonderworldofbooks.blogspot.de" },
    {
        "url": "http://www.mariessalondulivre.at",
        "titleSelector": ".art-postheader"
    },
    { "url": "http://www.misspaperback.de" },
    {
        "url": "http://buecher-liebe.de",
        "titleSelector": ".admania_entrytitle",
        "articleSelector": ".admania_entrycontent"
    },
    {
        "url": "http://www.tiefseezeilen.de",
        "useFallbackDateFromUrl": true
    },
    { "url": "https://tamiisbuecherblog.blogspot.de" },
    {
      "url": "https://acityofbooksblog.blogspot.de",
      "useFallbackDateFromUrl": true
    },
    { "url": "http://www.sommerdiebe.de" },
    { "url": "http://literaturmonster.de" },
    { "url": "https://pineapplesbooknook.wordpress.com" },
    { "url": "https://empty-bookshelves.blog" },
    { "url": "https://sandraskreativelesezeit.blogspot.de" },
    { "url": "https://lifesayshello.com" },
    { "url": "https://carmensbuecherkabinett.de" },
    { "url": "https://kitsunebooks.de" },
    { "url": "https://theworldofvioletbooklady.blogspot.de" },
    {
      "url": "https://fraeuleinnerdette.blogspot.de",
      "useFallbackDateFromUrl": true
    },
    { "url": "https://lifeofaboredgirl.wordpress.com" },
    { "url": "https://pantaubooks.wordpress.com" },
    { "url": "https://frannytastic.wordpress.com" },
    { "url": "https://nichtohnemeinbuch.com" },
    {
      "url": "https://lisasonnenschein.blogspot.de",
      "titleSelector": "#post .title a"
    },
    { "url": "https://literaturgarten.blogspot.de" },
    { "url": "https://einebuecherwelt.blogspot.de" },
    { "url": "https://derbuecherkessel.blogspot.de" },
    { "url": "https://moyasbuchgewimmel.de" },
    { "url": "https://phelmas.wordpress.com" },
    { "url": "https://eska-kreativ.blogspot.de" },
    { "url": "https://beccawithlovewuhuxoo.wordpress.com" },
    { "url": "https://www.buchbahnhof.de" },
    { "url": "https://little-miss-head-in-the-clouds.blogspot.de" },
    { "url": "https://libri-mundi.blogspot.de" },
    { "url": "https://bookcrow.wordpress.com" },
    { "url": "http://buchlingreport.de" },
    { "url": "https://samtpfotenleserei.wordpress.com" },
    { "url": "https://www.kinderbuchlesen.de" },
    { "url": "https://hoshiswunderland.blogspot.de" },
    { "url": "http://www.damarisliest-mini.de" },
    { "url": "https://buechereckenliebe.wordpress.com" },
    { "url": "http://buecher.fl-e.de" },
    { "url": "http://www.mokita.de/blog/" },
    { "url": "http://www.aureasfabelhaftewelt.com" },
    { "url": "https://bigben666.blog" },
    { "url": "https://feesbuecher.blogspot.de" },
    { "url": "https://traumfeder.blogspot.de" },
    { "url": "https://fiktivewelten.wordpress.com" },
    { "url": "http://www.die-fantastische-buecherwelt.de" },
    {
        "url": "https://love-whati-do.blogspot.de",
        "titleSelector": ".post h3.post-title.entry-title"
    },
    { "url": "https://buchstabenschatz.blogspot.de" },
    { "url": "https://hanniinnah.blogspot.de" },
    { "url": "https://tastenklecks.blogspot.de" },
    { "url": "https://prettytigerbuch.blogspot.de" },
    { "url": "https://schwarzbuntgestreift.com" },
    { "url": "https://lenareads.blogspot.de" },
    { "url": "https://bookwormdreamers.blogspot.de" },
    { "url": "https://www.kleiner-komet.de" },
    { "url": "https://sunnysmagicbooks.blogspot.de" },
    {
        "url": "http://www.handchosenbooks.com",
        "simulateBrowser": true,
        "isArticlePagePattern": "(portfolio_page/)",
        "titleSelector": ".portfolio_single h3",
        "articleSelector": ".portfolio_single",
        "ignoreDate": true
    },
    { "url": "https://ullasleseecke.blogspot.de" },
    { "url": "https://buchstabenmagie.blogspot.de" },
    { "url": "https://bookshelfnews.wordpress.com" },
    { "url": "https://lit-marcel.blogspot.de" },
    { "url": "https://www.anjas-insel.de" },
    { "url": "https://crimealleyblog.wordpress.com" },
    {
        "url": "https://www.epilogues.de",
        "simulateBrowser": true,
        "titleSelector": "h2.blog-details-headline"
    },
    { "url": "https://lesbarderbuecherblog.wordpress.com" },
    {
        "url": "https://die-welt-ist-ein-buch.blogspot.de",
        "useFallbackDateFromUrl": true
    },
    { "url": "https://abookishloveaffaire.blogspot.de" },
    { "url": "https://mellisbuchleben.blogspot.de" },
    { "url": "https://leelouswelt.blogspot.de" },
    { "url": "https://larasbibliothek.blogspot.de" },
    { "url": "https://captainbooksweb.wordpress.com" },
    { "url": "http://tommiunddieschmoeker.de" },
    {
        "url": "http://franzi-liest.de",
        "frame": "http://franzi-liest.de/wp/"
    },
    { "url": "https://hannasbuecherwelt.blogspot.de" },
    { "url": "http://pinkmitglitzer.de" },
    { "url": "http://little-dhampir.de" },
    {
        "url": "https://books-affair.blogspot.de",
        "titleSelector": ".post h3.post-title.entry-title"
    },
    { "url": "https://elmaliest.wordpress.com" },
    { "url": "http://www.team-buchmagie.de" },
    { "url": "https://bookbroker.wordpress.com" },
    { "url": "https://buecherpandablog.wordpress.com" },
    { "url": "https://calliewonderwood.blogspot.de" },
    { "url": "http://seitenfresserchen.de" },
    {
      "url": "https://annes-buecherwelt.blogspot.de",
      "useFallbackDateFromUrl": true
    },
    { "url": "http://www.danara-devries.de" },
    { "url": "https://gweesbuecherwelt.blogspot.de" },
    {
        "url": "http://schoenebuecher.uberfalk.de",
        "useFallbackDateFromUrl": true
    },
    { "url": "https://janinliest.wordpress.com" },
    {
        "url": "https://schreibblogg.de",
        "isArticlePageSelector": "body.singular"
    },
    { "url": "http://steffiliest.de" },
    { "url": "https://lesepanda.blogspot.de" },
    { "url": "https://once-uponastory.blogspot.de" },
    { "url": "https://buecherspiegel.wordpress.com" },
    { "url": "https://booksloveforeveryone.jimdo.com" },
    { "url": "http://www.zeilenmalerei.de" },
    { "url": "https://libroscope.wordpress.com" },
    { "url": "https://lauras-leseecke.blogspot.de" },
    { "url": "https://www.tintentaucher.de" },
    { "url": "https://jelimuki.de" },
    { "url": "http://www.booktopia.de" },
    { "url": "https://silverbooksblog.wordpress.com" },
    { "url": "https://nichtohnebuch.blogspot.de" },
    { "url": "https://bettysweltblog.wordpress.com" },
    { "url": "http://portablemagicpages.com" },
    { "url": "https://mademoiselle-cake-liest.blogspot.de" },
    { "url": "https://sabzbuecherblog.blogspot.de" },
    { "url": "http://goldblatt-blog.de" },
    { "url": "https://culalaliest.wordpress.com" },
    { "url": "http://www.buecherfansite.com" },
    {
        "url": "https://tricksareeverywere.blogspot.de",
        "titleSelector": ".blog-posts .post h3.post-title"
    },
    { "url": "http://www.hochhorst.de" },
    { "url": "https://ladylay2017.wordpress.com" },
    { "url": "https://meinleseblog.blogspot.de" },
    { "url": "https://booksterhro.wordpress.com" },
    { "url": "https://www.monawest.de" },
    {
        "url": "http://katesbuecherregal.de",
        "simulateBrowser": true,
        "titleSelector": ".nicole_post_title"
    },
    { "url": "https://buecherhexenwelt.blogspot.de" },
    { "url": "https://krimines-buecherblog.blogspot.de" },
    { "url": "https://martinasbuchwelten.blogspot.de" },
    { "url": "https://einbuchkommtseltenallein.wordpress.com" },
    { "url": "http://www.isleofbookx.at" },
    { "url": "https://www.derteufeltraegtbrille.de" },
    { "url": "https://book2pia.wordpress.com" },
    { "url": "https://jljordan.net" },
    { "url": "http://jeanparkersworld.de" },
    { "url": "https://laemmchenblog.wordpress.com" },
    { "url": "https://literaturreich.wordpress.com" },
    { "url": "https://trallafittibooks.com" },
    { "url": "http://www.buecher-kater-tee.de" },
    { "url": "http://madameklappentext.de" },
    { "url": "http://www.kulturernten.com" },
    { "url": "https://spperlen.wordpress.com" },
    { "url": "http://michelle-books.de" },
    { "url": "https://herzensbuecher.blog" },
    { "url": "https://stephaniemueller.net" },
    { "url": "https://niasbuecherwelt.wordpress.com" },
    {
      "url": "https://bella2108.blogspot.de",
      "useFallbackDateFromUrl": true
    },
    { "url": "https://memoriesofbooksss.blogspot.de" },
    { "url": "http://melusineswelt.de" },
    {
        "url": "http://buchwegweiser.com",
        "titleSelector": "h1.post-title.entry-title"
    },
    { "url": "https://schmoekerwelten.wordpress.com" },
    { "url": "https://fluffywordsblog.wordpress.com" },
    { "url": "https://ladysmartypants.wordpress.com" },
    { "url": "https://sandrasbookcorner.blogspot.de" },
    { "url": "https://buechermomente.com" },
    { "url": "https://dailylovebook.blogspot.de" },
    { "url": "http://www.glitzerkonfetti.de" },
    { "url": "https://bouquineurblog.wordpress.com" },
    { "url": "https://buchkatzeblog.wordpress.com" },
    { "url": "https://booksnights.blogspot.de" },
    { "url": "http://www.leipziglauscht.de" },
    { "url": "https://elisbuecherecke.blogspot.de" },
    { "url": "https://zauberhaftelesestunden.wordpress.com" },
    { "url": "http://www.gedanken-vielfalt.de" },
    { "url": "http://www.pinkmaibooks.de" },
    { "url": "http://zwischendenzeilengelesen.de" },
    { "url": "https://like-jackandsallysbooks.blogspot.de" },
    { "url": "https://the-passion-of-books.blogspot.de" },
    { "url": "https://herzdeinbuch.wordpress.com" },
    {
        "url": "https://eshleibook.blogspot.de",
        "useFallbackDateFromUrl": true
    },
    { "url": "https://zwischenweltlerinblog.wordpress.com" },
    {
        "url": "https://www.bellaswonderworld.de",
        "titleSelector": "h2.post_name"
    },
    { "url": "https://the-booklounge.blogspot.de" },
    { "url": "https://sasas-leseecke.blogspot.de" },
    { "url": "https://buchvogel.blogspot.de" },
    { "url": "http://selbstgelesen.de" },
    { "url": "https://livricieux.wordpress.com" },
    { "url": "https://juliasleseblog.blogspot.de" },
    { "url": "https://kleinlexibooks.com" },
    { "url": "https://buchdrache.blogspot.de" },
    { "url": "https://sweetlybutton.wordpress.com" },
    { "url": "http://kejas-blogbuch.de" },
    {
        "url": "http://findosbuecher.com",
        "titleSelector": "article h1.entry-title"
    },
    { "url": "https://printbalance.blogspot.de" },
    { "url": "https://amirasbibliothek.blogspot.de" },
    { "url": "https://monsterlillyswortliebe.wordpress.com" },
    { "url": "https://koreander.net" },
    { "url": "http://www.buchrebellin.de" },
    { "url": "https://www.mein-gluecksleseletter.de" },
    { "url": "https://buecherlilien.blogspot.de" },
    { "url": "http://blog-a-holic.de" },
    { "url": "https://letterheart.de" },
    { "url": "https://federecke.de" },
    { "url": "http://www.julias-wunderland.ch" },
    { "url": "https://lenasbooksecrets.blogspot.de" },
    { "url": "https://wortedeswiderstands.org" },
    { "url": "https://deineweltmeinewelt.blogspot.de" },
    { "url": "https://fraeuleinzeilenliebe.blogspot.de" },
    { "url": "https://meinlesezauber.blogspot.de" },
    { "url": "http://himmelsblau.org" },
    { "url": "https://ivybooknerd.com" },
    { "url": "https://hunderttausendbuecher.wordpress.com" },
    { "url": "https://papierheldenblog.wordpress.com" },
    { "url": "https://literaturwerkstattkreativblog.wordpress.com" },
    { "url": "https://buecher-palast.blogspot.de" },
    { "url": "https://sonjasunshinebooks.blogspot.de" },
    { "url": "https://hundimbuch.blog" },
    {
        "url": "https://seitenatlas.blogspot.de",
        "titleSelector": ".post h3.post-title.entry-title"
    },
    { "url": "https://mausisleselust.blogspot.de" },
    { "url": "https://lieblingsleseplatz.wordpress.com" },
    { "url": "https://leselustbuecher.blogspot.de" },
    { "url": "http://wortkunstsalat.de" },
    { "url": "https://tintenkompass.blogspot.de" },
    { "url": "https://bookinghampalaceblog.wordpress.com" },
    { "url": "https://krimisofa.com" },
    { "url": "https://leasbuchblog.blogspot.de" },
    { "url": "https://buecherregalschaetze.blogspot.de" },
    { "url": "https://literaturblatt.ch" },
    { "url": "https://wirbuchgeschwister.wordpress.com" },
    { "url": "https://monesblogwelt.blogspot.de" },
    { "url": "https://trinasbuecherwelt.wordpress.com" },
    { "url": "http://neomiscrazyworld.de" },
    { "url": "http://alexander-baumbach.de" },
    { "url": "https://secretbookchamber.wordpress.com" },
    { "url": "https://honestbooktalk.blogspot.de" },
    { "url": "https://wiebipeters.com" },
    { "url": "https://sarahricchizzi.com" },
    { "url": "https://chaoskingdom.wordpress.com" },
    { "url": "http://xn--mit-bchern-um-die-welt-wlc.de" },
    { "url": "https://kunterbuntesbuecherregal.wordpress.com" },
    {
        "url": "http://www.lesbar.blog",
        "ignoreUrl": [ "eventkalender", "?plugin" ]
    },
    { "url": "https://janinesbookworld.blogspot.de" },
    { "url": "http://allmeinetraeume.de" },
    {
        "url": "http://www.ladylay.de",
        "frame": "http://lr-develop.de/franziskasWordpress/"
    },
    { "url": "https://100geschichten.blog" },
    { "url": "https://jutini72.blogspot.de" },
    { "url": "https://buchhaim.com" },
    { "url": "http://www.literaturpost.de" },
    { "url": "http://www.back-down-to-earth.de" },
    { "url": "https://lese-magie.blogspot.de" },
    { "url": "https://annesleselisten.wordpress.com" },
    { "url": "https://laputasbuecherwelt.wordpress.com" },
    {
        "url": "https://minky-loves-to-read.blogspot.de",
        "titleSelector": "article h1.post-title.entry-title",
        "useFallbackDateFromUrl": true
    },
    { "url": "https://poesielos.blog" },
    { "url": "https://www.booknapping.de" },
    { "url": "https://heftehaufen.blogspot.de" },
    { "url": "http://shanlira.de" },
    { "url": "https://a-winterstory.blogspot.de" },
    { "url": "http://leselaunen.net" },
    { "url": "http://talesandmemories.de" },
    {
        "url": "https://immerlesen.net",
        "titleSelector": ".fl-heading-text",
        "articleSelector": ".fl-module-fl-post-content",
        "dateSelector": "script"
    },
    { "url": "https://buntebuecherwelten.wordpress.com" },
    { "url": "http://thebookbeast.de" },
    { "url": "https://lilaliest.blogspot.de" },
    { "url": "https://lilibookworm.wordpress.com" },
    { "url": "http://www.pm-thinks.com" },
    { "url": "http://www.nisnis-buecherliebe.de" },
    { "url": "http://read-eat.de" },
    { "url": "https://geschichtentaucher.wordpress.com" },
    { "url": "https://kinderbuchexperten.wordpress.com" },
    { "url": "https://meermoabit.wordpress.com" },
    { "url": "https://bookishmoments.blogspot.de" },
    { "url": "https://wurmsuchtbuch.com" },
    { "url": "https://bookprincessbysarah.wordpress.com" },
    { "url": "https://lexasleben.de" },
    { "url": "https://meinbuecherregalundich.blogspot.de" },
    { "url": "https://lady-firesbuchblog.blogspot.de" },
    { "url": "https://ellawoodwater.com" },
    { "url": "https://zauberhaftebuecherwelten.blogspot.de" },
    { "url": "https://thebookandtheowl.wordpress.com" },
    { "url": "https://federmaedchensfederwelt.blogspot.de" },
    {
        "url": "https://majasbuecherliebe.blogspot.de",
        "titleSelector": ".post h3.post-title.entry-title"
    },
    { "url": "http://gochimiko.de" },
    { "url": "https://leseninvollenzuegen.wordpress.com" },
    {
        "url": "https://perspektivenundblickwinkel.wordpress.com",
        "titleSelector": "#masthead h1.entry-title"
    },
    { "url": "http://www.buchnotizen.de" },
    { "url": "https://gerngelesen.de" },
    { "url": "https://foryou-books.blogspot.de" },
    { "url": "https://libraryofworldsblog.wordpress.com" },
    { "url": "https://nimithil.blogspot.de" },
    { "url": "https://neniswelt.wordpress.com" },
    { "url": "http://buchbunt.blog" },
    { "url": "http://heart-moment.com" },
    { "url": "http://www.fraeulein-annemie.de" },
    { "url": "https://hundertmorgen-wald.blogspot.de" },
    { "url": "https://juliaslesewelten.blogspot.de" },
    { "url": "http://buchrezension-blog.de" },
    {
        "url": "http://bucheulchen.de",
        "removeSelector": [".widget_posts_list"]
    },
    { "url": "https://buchstudent.wordpress.com" },
    { "url": "http://ditundat.net" },
    { "url": "https://rikasbookshelf.wordpress.com" },
    { "url": "http://buchworte.de" },
    { "url": "https://literaturblogsaarland.wordpress.com" },
    { "url": "https://literaturhandbuch.de" },
    { "url": "https://iamnomorningperson.blogspot.de" },
    { "url": "https://boooksoffantasy.blogspot.de" },
    { "url": "https://weltenbastlerin.wordpress.com" },
    { "url": "https://marissaconrady.wordpress.com" },
    { "url": "https://buch-rezensionen.blog" },
    { "url": "http://www.laubet.de" },
    { "url": "https://imbuecherzelt.wordpress.com" },
    { "url": "https://annichansfantasticbooks.wordpress.com" },
    { "url": "http://fay-readme.de" },
    { "url": "http://dasbuecherregal.de" },
    { "url": "https://momentfluesterin.blogspot.de" },
    { "url": "http://sachbuch-rezensionen.de" },
    {
        "url": "https://moniszeitreise.blogspot.de",
        "simulateBrowser": true
    },
    { "url": "https://www.wortverdichtung.de" },
    { "url": "https://kointashobbyecke.blogspot.de" },
    { "url": "https://seehases-lesewelt.blogspot.de" },
    { "url": "https://buecherundkunst.wordpress.com" },
    { "url": "https://einweitererliteraturblog.wordpress.com" },
    { "url": "http://buecherfarben.de" },
    { "url": "http://www.buecherreh.at" },
    { "url": "https://herbstmosaik.wordpress.com" },
    { "url": "https://chillys-buchwelt.blogspot.de" },
    { "url": "https://www.elchisworldofbooksandcrafts.de" },
    { "url": "http://printedpages.de" },
    { "url": "http://nerdahoi.de" },
    { "url": "https://mellisbuecherliebe.blogspot.de" },
    {
        "url": "https://weltenfuchs.blogspot.de",
        "preScanMinPageCount": 2
    },
    { "url": "https://herzgespenster.blogspot.de" },
    {
        "url": "https://www.buecherrezensionen.org",
        "isArticlePagePattern": "/buecher/*",
        "dateSelector": ".meta",
        "titleSelector": "h3 span[itemprop=headline]",
        "articleSelector": ".article"
    },
    { "url": "https://wortmeer.blog" },
    {
        "url": "https://www.endloseseiten.de",
        "useFallbackDateFromUrl": true
    },
    { "url": "http://madame-vegan.de" },
    { "url": "https://schneidering.de" },
    { "url": "https://theophlia69.wordpress.com" },
    { "url": "https://moiraamannweiser.wordpress.com" },
    { "url": "https://librispoison.blogspot.de" },
    { "url": "http://cleo-schreiber.blogspot.de" },
    { "url": "http://buchgefunden.de" },
    { "url": "http://franzi-liest.de/wp" },
    { "url": "https://xmissxunicornx.blogspot.de" },
    { "url": "https://lectitare.blogspot.de" },
    { "url": "http://bookiedreams.blogspot.de" },
    { "url": "https://readbooksandfallinlove.com" },
    { "url": "http://www.crowandkraken.de" },
    { "url": "https://barbarasparadies.blogspot.de" },
    { "url": "http://lebenslaunen.blogspot.de" },
    { "url": "http://www.sharonbakerliest.de" },
    { "url": "http://buecher-an-bord.de" },
    { "url": "https://thrilling-books.blogspot.de" },
    { "url": "http://dieanderswelt.de" },
    { "url": "https://linda-liest.de" },
    { "url": "https://buecherwanderin.com" },
    { "url": "http://www.pigletandherbooks.de" },
    { "url": "https://serisadasblog.blogspot.de" },
    { "url": "http://victoriaskrams.de" },
    { "url": "https://leseninleipzigblog.wordpress.com" },
    { "url": "https://notizenderwaldgaengerin.blog" },
    {
        "url": "http://www.missfoxyreads.de",
        "titleSelector": ".tt-blog-head-inner h1.c-h1",
        "articleSelector": ".tt-content"
    },
	{ "url": "https://kunterbunteflaschenpost.de" },
	{ "url": "http://bluesiren.de" },
	{ "url": "https://bookstheessenceoflife.wordpress.com" },
	{ "url": "https://watchedstuff.wordpress.com" },
	{ "url": "https://www.vivarubia.ch" },
	{ "url": "https://soerenheim.wordpress.com" },
	{ "url": "https://rikerandom.de" },
	{ "url": "http://geekgefluester.de" },
	{ "url": "https://hufieslesestall.de" },
	{ "url": "http://buechertraum.com" },
	{ "url": "https://buchperlenblog.wordpress.com" },
	{ "url": "http://buchwegweiser.com" },
	{ "url": "http://www.vollysbuecher.de" },
	{ "url": "https://chrissies-blogwelt.de" },
	{ "url": "https://mounddiemachtderbuchstaben.blogspot.de" },
	{ "url": "https://bluesiren.de" },
	{ "url": "https://meinschreibtagebuch.blogspot.de" },
	{ "url": "https://hashtag122552794.wordpress.com" },
	{ "url": "https://catherineoertel.wordpress.com" },
	{ "url": "http://inprogressx.blogspot.de" },
	{ "url": "https://pascalliest.wordpress.com" },
	{ "url": "https://maisonette501.jimdo.com/" },
	{ "url": "https://www.lesenmitlinks.de" }
]